{
  "_embedded" : {
    "areaOfConcern" : [ {
      "createdDate" : "2017-11-06T11:57:33.156+0000",
      "lastModifiedDate" : "2017-11-06T11:57:33.156+0000",
      "uuid" : "814082c6-9693-4d63-9ce8-45dad4cdc1ab",
      "inactive" : false,
      "name" : "Service Provision",
      "reference" : "A",
      "_links" : {
        "self" : {
          "href" : "/1"
        },
        "areaOfConcern" : {
          "href" : "/1"
        },
        "standards" : {
          "href" : "/1/standards"
        },
        "checklists" : {
          "href" : "/1/checklists"
        }
      }
    }, {
      "createdDate" : "2017-11-06T11:57:33.323+0000",
      "lastModifiedDate" : "2017-11-06T11:57:33.323+0000",
      "uuid" : "114be617-f367-4034-97ff-18ef396eb68d",
      "inactive" : false,
      "name" : "Patient Rights",
      "reference" : "B",
      "_links" : {
        "self" : {
          "href" : "/2"
        },
        "areaOfConcern" : {
          "href" : "/2"
        },
        "standards" : {
          "href" : "/2/standards"
        },
        "checklists" : {
          "href" : "/2/checklists"
        }
      }
    }, {
      "createdDate" : "2017-11-06T11:57:33.497+0000",
      "lastModifiedDate" : "2017-11-06T11:57:33.497+0000",
      "uuid" : "e70bd204-eebd-40ad-9f85-bc97fb05ea4b",
      "inactive" : false,
      "name" : "Inputs",
      "reference" : "C",
      "_links" : {
        "self" : {
          "href" : "/3"
        },
        "areaOfConcern" : {
          "href" : "/3"
        },
        "standards" : {
          "href" : "/3/standards"
        },
        "checklists" : {
          "href" : "/3/checklists"
        }
      }
    }, {
      "createdDate" : "2017-11-06T11:57:33.677+0000",
      "lastModifiedDate" : "2017-11-06T11:57:33.677+0000",
      "uuid" : "7adf4405-da4c-4ef6-abea-c0815d546b83",
      "inactive" : false,
      "name" : "Support Services",
      "reference" : "D",
      "_links" : {
        "self" : {
          "href" : "/4"
        },
        "areaOfConcern" : {
          "href" : "/4"
        },
        "standards" : {
          "href" : "/4/standards"
        },
        "checklists" : {
          "href" : "/4/checklists"
        }
      }
    }, {
      "createdDate" : "2017-11-06T11:57:34.026+0000",
      "lastModifiedDate" : "2017-11-06T11:57:34.026+0000",
      "uuid" : "47eae108-5d82-4600-8802-35db174e34eb",
      "inactive" : false,
      "name" : "Clinical Services",
      "reference" : "E",
      "_links" : {
        "self" : {
          "href" : "/5"
        },
        "areaOfConcern" : {
          "href" : "/5"
        },
        "standards" : {
          "href" : "/5/standards"
        },
        "checklists" : {
          "href" : "/5/checklists"
        }
      }
    }, {
      "createdDate" : "2017-11-06T11:57:34.208+0000",
      "lastModifiedDate" : "2017-11-06T11:57:34.208+0000",
      "uuid" : "17bf89b4-8788-4a83-b288-3db0e24593d8",
      "inactive" : false,
      "name" : "Infection Control",
      "reference" : "F",
      "_links" : {
        "self" : {
          "href" : "/6"
        },
        "areaOfConcern" : {
          "href" : "/6"
        },
        "standards" : {
          "href" : "/6/standards"
        },
        "checklists" : {
          "href" : "/6/checklists"
        }
      }
    }, {
      "createdDate" : "2017-11-06T11:57:34.384+0000",
      "lastModifiedDate" : "2017-11-06T11:57:34.384+0000",
      "uuid" : "70dda9bf-482d-4d01-9506-ce51b6c825e2",
      "inactive" : false,
      "name" : "Quality Management",
      "reference" : "G",
      "_links" : {
        "self" : {
          "href" : "/7"
        },
        "areaOfConcern" : {
          "href" : "/7"
        },
        "standards" : {
          "href" : "/7/standards"
        },
        "checklists" : {
          "href" : "/7/checklists"
        }
      }
    }, {
      "createdDate" : "2017-11-06T11:57:34.559+0000",
      "lastModifiedDate" : "2017-11-06T11:57:34.559+0000",
      "uuid" : "fe41d6af-1fee-489c-8d57-efbc2e905858",
      "inactive" : false,
      "name" : "Outcome",
      "reference" : "H",
      "_links" : {
        "self" : {
          "href" : "/8"
        },
        "areaOfConcern" : {
          "href" : "/8"
        },
        "standards" : {
          "href" : "/8/standards"
        },
        "checklists" : {
          "href" : "/8/checklists"
        }
      }
    }, {
      "createdDate" : "2017-11-06T11:57:34.732+0000",
      "lastModifiedDate" : "2017-11-06T11:57:34.732+0000",
      "uuid" : "c9c0cab1-fded-4fb2-b043-0af8951e5b50",
      "inactive" : false,
      "name" : "Service Provision",
      "reference" : "A",
      "_links" : {
        "self" : {
          "href" : "/9"
        },
        "areaOfConcern" : {
          "href" : "/9"
        },
        "standards" : {
          "href" : "/9/standards"
        },
        "checklists" : {
          "href" : "/9/checklists"
        }
      }
    }, {
      "createdDate" : "2017-11-06T11:57:35.074+0000",
      "lastModifiedDate" : "2017-11-06T11:57:35.074+0000",
      "uuid" : "4e9b868c-3ae2-4d49-b593-b54fb85d9854",
      "inactive" : false,
      "name" : "Patient Rights",
      "reference" : "B",
      "_links" : {
        "self" : {
          "href" : "/10"
        },
        "areaOfConcern" : {
          "href" : "/10"
        },
        "standards" : {
          "href" : "/10/standards"
        },
        "checklists" : {
          "href" : "/10/checklists"
        }
      }
    }, {
      "createdDate" : "2017-11-06T11:57:35.440+0000",
      "lastModifiedDate" : "2017-11-06T11:57:35.440+0000",
      "uuid" : "0f26e600-56da-4908-a5bc-7f2f7239007f",
      "inactive" : false,
      "name" : "Inputs",
      "reference" : "C",
      "_links" : {
        "self" : {
          "href" : "/11"
        },
        "areaOfConcern" : {
          "href" : "/11"
        },
        "standards" : {
          "href" : "/11/standards"
        },
        "checklists" : {
          "href" : "/11/checklists"
        }
      }
    }, {
      "createdDate" : "2017-11-06T11:57:35.656+0000",
      "lastModifiedDate" : "2017-11-06T11:57:35.656+0000",
      "uuid" : "afc0f10d-d80c-4444-ad89-db2e50199a87",
      "inactive" : false,
      "name" : "Support Services",
      "reference" : "D",
      "_links" : {
        "self" : {
          "href" : "/12"
        },
        "areaOfConcern" : {
          "href" : "/12"
        },
        "standards" : {
          "href" : "/12/standards"
        },
        "checklists" : {
          "href" : "/12/checklists"
        }
      }
    }, {
      "createdDate" : "2017-11-06T11:57:35.839+0000",
      "lastModifiedDate" : "2017-11-06T11:57:35.839+0000",
      "uuid" : "f118aa98-f440-46d1-8ddb-88a77a9eda05",
      "inactive" : false,
      "name" : "Clinical Services",
      "reference" : "E",
      "_links" : {
        "self" : {
          "href" : "/13"
        },
        "areaOfConcern" : {
          "href" : "/13"
        },
        "standards" : {
          "href" : "/13/standards"
        },
        "checklists" : {
          "href" : "/13/checklists"
        }
      }
    }, {
      "createdDate" : "2017-11-06T11:57:36.155+0000",
      "lastModifiedDate" : "2017-11-06T11:57:36.155+0000",
      "uuid" : "1b45e630-7d16-49a8-8a5f-f8afdc1dd749",
      "inactive" : false,
      "name" : "Infection Control",
      "reference" : "F",
      "_links" : {
        "self" : {
          "href" : "/14"
        },
        "areaOfConcern" : {
          "href" : "/14"
        },
        "standards" : {
          "href" : "/14/standards"
        },
        "checklists" : {
          "href" : "/14/checklists"
        }
      }
    }, {
      "createdDate" : "2017-11-06T11:57:36.372+0000",
      "lastModifiedDate" : "2017-11-06T11:57:36.372+0000",
      "uuid" : "3ce6c0bf-cbd4-4a43-a88e-19f56f26f2b1",
      "inactive" : false,
      "name" : "Quality Management",
      "reference" : "G",
      "_links" : {
        "self" : {
          "href" : "/15"
        },
        "areaOfConcern" : {
          "href" : "/15"
        },
        "standards" : {
          "href" : "/15/standards"
        },
        "checklists" : {
          "href" : "/15/checklists"
        }
      }
    }, {
      "createdDate" : "2017-11-06T11:57:36.648+0000",
      "lastModifiedDate" : "2017-11-06T11:57:36.648+0000",
      "uuid" : "2d3109b7-72d8-4758-9812-f2cdf307838e",
      "inactive" : false,
      "name" : "Outcome",
      "reference" : "H",
      "_links" : {
        "self" : {
          "href" : "/16"
        },
        "areaOfConcern" : {
          "href" : "/16"
        },
        "standards" : {
          "href" : "/16/standards"
        },
        "checklists" : {
          "href" : "/16/checklists"
        }
      }
    }, {
      "createdDate" : "2017-11-06T11:57:36.961+0000",
      "lastModifiedDate" : "2017-11-06T11:57:36.961+0000",
      "uuid" : "d3cda284-fab6-45d4-b611-f73281ccfa3a",
      "inactive" : false,
      "name" : "Service Provision",
      "reference" : "A",
      "_links" : {
        "self" : {
          "href" : "/17"
        },
        "areaOfConcern" : {
          "href" : "/17"
        },
        "standards" : {
          "href" : "/17/standards"
        },
        "checklists" : {
          "href" : "/17/checklists"
        }
      }
    }, {
      "createdDate" : "2017-11-06T11:57:37.170+0000",
      "lastModifiedDate" : "2017-11-06T11:57:37.170+0000",
      "uuid" : "950d79f5-f306-4417-a8ab-12c3d836f003",
      "inactive" : false,
      "name" : "Patient Rights",
      "reference" : "B",
      "_links" : {
        "self" : {
          "href" : "/18"
        },
        "areaOfConcern" : {
          "href" : "/18"
        },
        "standards" : {
          "href" : "/18/standards"
        },
        "checklists" : {
          "href" : "/18/checklists"
        }
      }
    }, {
      "createdDate" : "2017-11-06T11:57:37.346+0000",
      "lastModifiedDate" : "2017-11-06T11:57:37.346+0000",
      "uuid" : "bdec90f8-080c-4e3c-81cb-df440a5ddea4",
      "inactive" : false,
      "name" : "Inputs",
      "reference" : "C",
      "_links" : {
        "self" : {
          "href" : "/19"
        },
        "areaOfConcern" : {
          "href" : "/19"
        },
        "standards" : {
          "href" : "/19/standards"
        },
        "checklists" : {
          "href" : "/19/checklists"
        }
      }
    }, {
      "createdDate" : "2017-11-06T11:57:37.526+0000",
      "lastModifiedDate" : "2017-11-06T11:57:37.526+0000",
      "uuid" : "a30b5216-511f-47eb-b368-85227eb4b4b4",
      "inactive" : false,
      "name" : "Support Services",
      "reference" : "D",
      "_links" : {
        "self" : {
          "href" : "/20"
        },
        "areaOfConcern" : {
          "href" : "/20"
        },
        "standards" : {
          "href" : "/20/standards"
        },
        "checklists" : {
          "href" : "/20/checklists"
        }
      }
    }, {
      "createdDate" : "2017-11-06T11:57:37.704+0000",
      "lastModifiedDate" : "2017-11-06T11:57:37.704+0000",
      "uuid" : "04b2a148-ed99-4632-b844-b41daecaeeea",
      "inactive" : false,
      "name" : "Clinical Services",
      "reference" : "E",
      "_links" : {
        "self" : {
          "href" : "/21"
        },
        "areaOfConcern" : {
          "href" : "/21"
        },
        "standards" : {
          "href" : "/21/standards"
        },
        "checklists" : {
          "href" : "/21/checklists"
        }
      }
    }, {
      "createdDate" : "2017-11-06T11:57:37.975+0000",
      "lastModifiedDate" : "2017-11-06T11:57:37.975+0000",
      "uuid" : "87689cd1-a2bb-46db-aa0a-b153df4a5eb2",
      "inactive" : false,
      "name" : "Infection Control",
      "reference" : "F",
      "_links" : {
        "self" : {
          "href" : "/22"
        },
        "areaOfConcern" : {
          "href" : "/22"
        },
        "standards" : {
          "href" : "/22/standards"
        },
        "checklists" : {
          "href" : "/22/checklists"
        }
      }
    }, {
      "createdDate" : "2017-11-06T11:57:38.190+0000",
      "lastModifiedDate" : "2017-11-06T11:57:38.190+0000",
      "uuid" : "b786f07f-4c89-4dff-b61f-1f6889901f45",
      "inactive" : false,
      "name" : "Quality Management",
      "reference" : "G",
      "_links" : {
        "self" : {
          "href" : "/23"
        },
        "areaOfConcern" : {
          "href" : "/23"
        },
        "standards" : {
          "href" : "/23/standards"
        },
        "checklists" : {
          "href" : "/23/checklists"
        }
      }
    }, {
      "createdDate" : "2017-11-06T11:57:38.367+0000",
      "lastModifiedDate" : "2017-11-06T11:57:38.367+0000",
      "uuid" : "eede4a4d-c3b3-46d6-a6cc-9ec1f022f864",
      "inactive" : false,
      "name" : "Outcomes",
      "reference" : "H",
      "_links" : {
        "self" : {
          "href" : "/24"
        },
        "areaOfConcern" : {
          "href" : "/24"
        },
        "standards" : {
          "href" : "/24/standards"
        },
        "checklists" : {
          "href" : "/24/checklists"
        }
      }
    }, {
      "createdDate" : "2017-11-06T11:57:38.546+0000",
      "lastModifiedDate" : "2017-11-06T11:57:38.546+0000",
      "uuid" : "7f489a2c-5540-4373-a3f4-567e875b1789",
      "inactive" : false,
      "name" : "Service Provision",
      "reference" : "A",
      "_links" : {
        "self" : {
          "href" : "/25"
        },
        "areaOfConcern" : {
          "href" : "/25"
        },
        "standards" : {
          "href" : "/25/standards"
        },
        "checklists" : {
          "href" : "/25/checklists"
        }
      }
    }, {
      "createdDate" : "2017-11-06T11:57:38.721+0000",
      "lastModifiedDate" : "2017-11-06T11:57:38.721+0000",
      "uuid" : "7d67de00-243a-45b6-bc5a-60e16ed0dbbd",
      "inactive" : false,
      "name" : "Patient Rights",
      "reference" : "B",
      "_links" : {
        "self" : {
          "href" : "/26"
        },
        "areaOfConcern" : {
          "href" : "/26"
        },
        "standards" : {
          "href" : "/26/standards"
        },
        "checklists" : {
          "href" : "/26/checklists"
        }
      }
    }, {
      "createdDate" : "2017-11-06T11:57:38.996+0000",
      "lastModifiedDate" : "2017-11-06T11:57:38.996+0000",
      "uuid" : "1b82e2db-6242-419b-aff7-63cbe1aa2a42",
      "inactive" : false,
      "name" : "Inputs",
      "reference" : "C",
      "_links" : {
        "self" : {
          "href" : "/27"
        },
        "areaOfConcern" : {
          "href" : "/27"
        },
        "standards" : {
          "href" : "/27/standards"
        },
        "checklists" : {
          "href" : "/27/checklists"
        }
      }
    }, {
      "createdDate" : "2017-11-06T11:57:39.212+0000",
      "lastModifiedDate" : "2017-11-06T11:57:39.212+0000",
      "uuid" : "b97337dd-12e4-40f4-9af5-f1aa38495dd2",
      "inactive" : false,
      "name" : "Support Services",
      "reference" : "D",
      "_links" : {
        "self" : {
          "href" : "/28"
        },
        "areaOfConcern" : {
          "href" : "/28"
        },
        "standards" : {
          "href" : "/28/standards"
        },
        "checklists" : {
          "href" : "/28/checklists"
        }
      }
    }, {
      "createdDate" : "2017-11-06T11:57:39.388+0000",
      "lastModifiedDate" : "2017-11-06T11:57:39.388+0000",
      "uuid" : "91da1dc8-f010-40c0-aaa1-c93a0b4cbc79",
      "inactive" : false,
      "name" : "Clinical Services",
      "reference" : "E",
      "_links" : {
        "self" : {
          "href" : "/29"
        },
        "areaOfConcern" : {
          "href" : "/29"
        },
        "standards" : {
          "href" : "/29/standards"
        },
        "checklists" : {
          "href" : "/29/checklists"
        }
      }
    }, {
      "createdDate" : "2017-11-06T11:57:39.559+0000",
      "lastModifiedDate" : "2017-11-06T11:57:39.559+0000",
      "uuid" : "af1c06f5-0dee-47c8-bf94-46280ff3c36d",
      "inactive" : false,
      "name" : "Infection Control",
      "reference" : "F",
      "_links" : {
        "self" : {
          "href" : "/30"
        },
        "areaOfConcern" : {
          "href" : "/30"
        },
        "standards" : {
          "href" : "/30/standards"
        },
        "checklists" : {
          "href" : "/30/checklists"
        }
      }
    }, {
      "createdDate" : "2017-11-06T11:57:39.737+0000",
      "lastModifiedDate" : "2017-11-06T11:57:39.737+0000",
      "uuid" : "bbe7fc5d-b25a-4a6a-9735-050a95bd33ad",
      "inactive" : false,
      "name" : "Quality Management",
      "reference" : "G",
      "_links" : {
        "self" : {
          "href" : "/31"
        },
        "areaOfConcern" : {
          "href" : "/31"
        },
        "standards" : {
          "href" : "/31/standards"
        },
        "checklists" : {
          "href" : "/31/checklists"
        }
      }
    }, {
      "createdDate" : "2017-11-06T11:57:40.053+0000",
      "lastModifiedDate" : "2017-11-06T11:57:40.053+0000",
      "uuid" : "9d512330-5a75-4a46-96a1-52fcdd68a051",
      "inactive" : false,
      "name" : "Outcomes",
      "reference" : "H",
      "_links" : {
        "self" : {
          "href" : "/32"
        },
        "areaOfConcern" : {
          "href" : "/32"
        },
        "standards" : {
          "href" : "/32/standards"
        },
        "checklists" : {
          "href" : "/32/checklists"
        }
      }
    }, {
      "createdDate" : "2017-11-06T11:57:40.231+0000",
      "lastModifiedDate" : "2017-11-06T11:57:40.231+0000",
      "uuid" : "2c3a53f3-4637-4a02-b7a9-306eafe2dd2e",
      "inactive" : false,
      "name" : "Hospital / Facility Upkeep",
      "reference" : "A",
      "_links" : {
        "self" : {
          "href" : "/33"
        },
        "areaOfConcern" : {
          "href" : "/33"
        },
        "standards" : {
          "href" : "/33/standards"
        },
        "checklists" : {
          "href" : "/33/checklists"
        }
      }
    }, {
      "createdDate" : "2017-11-06T11:57:40.324+0000",
      "lastModifiedDate" : "2017-11-06T11:57:40.324+0000",
      "uuid" : "db0add25-84df-4d3d-8d1b-ecff462a3a36",
      "inactive" : false,
      "name" : "Sanitation & Hygiene",
      "reference" : "B",
      "_links" : {
        "self" : {
          "href" : "/34"
        },
        "areaOfConcern" : {
          "href" : "/34"
        },
        "standards" : {
          "href" : "/34/standards"
        },
        "checklists" : {
          "href" : "/34/checklists"
        }
      }
    }, {
      "createdDate" : "2017-11-06T11:57:40.440+0000",
      "lastModifiedDate" : "2017-11-06T11:57:40.440+0000",
      "uuid" : "0e59b7d4-6b57-4550-9356-907d2f6ce8a9",
      "inactive" : false,
      "name" : "Waste Management",
      "reference" : "C",
      "_links" : {
        "self" : {
          "href" : "/35"
        },
        "areaOfConcern" : {
          "href" : "/35"
        },
        "standards" : {
          "href" : "/35/standards"
        },
        "checklists" : {
          "href" : "/35/checklists"
        }
      }
    }, {
      "createdDate" : "2017-11-06T11:57:40.535+0000",
      "lastModifiedDate" : "2017-11-06T11:57:40.535+0000",
      "uuid" : "4bf9fb69-1854-4093-8cc7-a772e507113c",
      "inactive" : false,
      "name" : "Infection Control",
      "reference" : "D",
      "_links" : {
        "self" : {
          "href" : "/36"
        },
        "areaOfConcern" : {
          "href" : "/36"
        },
        "standards" : {
          "href" : "/36/standards"
        },
        "checklists" : {
          "href" : "/36/checklists"
        }
      }
    }, {
      "createdDate" : "2017-11-06T11:57:40.630+0000",
      "lastModifiedDate" : "2017-11-06T11:57:40.630+0000",
      "uuid" : "13a09ca8-3d99-4d36-95c1-b89a66eddc64",
      "inactive" : false,
      "name" : "Support Services",
      "reference" : "E",
      "_links" : {
        "self" : {
          "href" : "/37"
        },
        "areaOfConcern" : {
          "href" : "/37"
        },
        "standards" : {
          "href" : "/37/standards"
        },
        "checklists" : {
          "href" : "/37/checklists"
        }
      }
    }, {
      "createdDate" : "2017-11-06T11:57:40.719+0000",
      "lastModifiedDate" : "2017-11-06T11:57:40.719+0000",
      "uuid" : "b335c24a-b461-4039-a829-bfcba0ce2dc5",
      "inactive" : false,
      "name" : "Hygiene Promotion",
      "reference" : "F",
      "_links" : {
        "self" : {
          "href" : "/38"
        },
        "areaOfConcern" : {
          "href" : "/38"
        },
        "standards" : {
          "href" : "/38/standards"
        },
        "checklists" : {
          "href" : "/38/checklists"
        }
      }
    }, {
      "createdDate" : "2017-11-06T11:57:40.810+0000",
      "lastModifiedDate" : "2017-11-06T11:57:40.810+0000",
      "uuid" : "f77139c5-57c2-4209-9603-af3068527dce",
      "inactive" : false,
      "name" : "PHC Upkeep",
      "reference" : "A",
      "_links" : {
        "self" : {
          "href" : "/39"
        },
        "areaOfConcern" : {
          "href" : "/39"
        },
        "standards" : {
          "href" : "/39/standards"
        },
        "checklists" : {
          "href" : "/39/checklists"
        }
      }
    }, {
      "createdDate" : "2017-11-06T11:57:40.946+0000",
      "lastModifiedDate" : "2017-11-06T11:57:40.946+0000",
      "uuid" : "f420210e-9a17-4c02-aa46-5d98ebbf7827",
      "inactive" : false,
      "name" : "Sanitation & Hygiene",
      "reference" : "B",
      "_links" : {
        "self" : {
          "href" : "/40"
        },
        "areaOfConcern" : {
          "href" : "/40"
        },
        "standards" : {
          "href" : "/40/standards"
        },
        "checklists" : {
          "href" : "/40/checklists"
        }
      }
    }, {
      "createdDate" : "2017-11-06T11:57:41.039+0000",
      "lastModifiedDate" : "2017-11-06T11:57:41.039+0000",
      "uuid" : "57155b3e-4c53-4caf-af73-e6bdfc7ac22e",
      "inactive" : false,
      "name" : "Waste Management",
      "reference" : "C",
      "_links" : {
        "self" : {
          "href" : "/41"
        },
        "areaOfConcern" : {
          "href" : "/41"
        },
        "standards" : {
          "href" : "/41/standards"
        },
        "checklists" : {
          "href" : "/41/checklists"
        }
      }
    }, {
      "createdDate" : "2017-11-06T11:57:41.260+0000",
      "lastModifiedDate" : "2017-11-06T11:57:41.260+0000",
      "uuid" : "35ae8c5b-39d0-4226-8afb-a904ed4a3b50",
      "inactive" : false,
      "name" : "Infection Control",
      "reference" : "D",
      "_links" : {
        "self" : {
          "href" : "/42"
        },
        "areaOfConcern" : {
          "href" : "/42"
        },
        "standards" : {
          "href" : "/42/standards"
        },
        "checklists" : {
          "href" : "/42/checklists"
        }
      }
    }, {
      "createdDate" : "2017-11-06T11:57:41.352+0000",
      "lastModifiedDate" : "2017-11-06T11:57:41.352+0000",
      "uuid" : "c4e29d5d-1c60-4010-9084-fb5ffa5eb479",
      "inactive" : false,
      "name" : "Support Services",
      "reference" : "E",
      "_links" : {
        "self" : {
          "href" : "/43"
        },
        "areaOfConcern" : {
          "href" : "/43"
        },
        "standards" : {
          "href" : "/43/standards"
        },
        "checklists" : {
          "href" : "/43/checklists"
        }
      }
    }, {
      "createdDate" : "2017-11-06T11:57:41.450+0000",
      "lastModifiedDate" : "2017-11-06T11:57:41.450+0000",
      "uuid" : "67db732b-9113-445f-a9d2-889473686277",
      "inactive" : false,
      "name" : "Hygiene Promotion",
      "reference" : "F",
      "_links" : {
        "self" : {
          "href" : "/44"
        },
        "areaOfConcern" : {
          "href" : "/44"
        },
        "standards" : {
          "href" : "/44/standards"
        },
        "checklists" : {
          "href" : "/44/checklists"
        }
      }
    }, {
      "createdDate" : "2017-11-06T11:57:41.554+0000",
      "lastModifiedDate" : "2017-11-06T11:57:41.554+0000",
      "uuid" : "8f08416b-95db-4d16-a099-1503c0257121",
      "inactive" : false,
      "name" : "PHC Upkeep",
      "reference" : "A",
      "_links" : {
        "self" : {
          "href" : "/45"
        },
        "areaOfConcern" : {
          "href" : "/45"
        },
        "standards" : {
          "href" : "/45/standards"
        },
        "checklists" : {
          "href" : "/45/checklists"
        }
      }
    }, {
      "createdDate" : "2017-11-06T11:57:41.653+0000",
      "lastModifiedDate" : "2017-11-06T11:57:41.653+0000",
      "uuid" : "2606d027-9a27-4c09-9042-c090e1220216",
      "inactive" : false,
      "name" : "Sanitation & Hygiene",
      "reference" : "B",
      "_links" : {
        "self" : {
          "href" : "/46"
        },
        "areaOfConcern" : {
          "href" : "/46"
        },
        "standards" : {
          "href" : "/46/standards"
        },
        "checklists" : {
          "href" : "/46/checklists"
        }
      }
    }, {
      "createdDate" : "2017-11-06T11:57:41.743+0000",
      "lastModifiedDate" : "2017-11-06T11:57:41.743+0000",
      "uuid" : "168810d9-9879-46fa-9501-7f4463db26e5",
      "inactive" : false,
      "name" : "Waste Management",
      "reference" : "C",
      "_links" : {
        "self" : {
          "href" : "/47"
        },
        "areaOfConcern" : {
          "href" : "/47"
        },
        "standards" : {
          "href" : "/47/standards"
        },
        "checklists" : {
          "href" : "/47/checklists"
        }
      }
    }, {
      "createdDate" : "2017-11-06T11:57:41.850+0000",
      "lastModifiedDate" : "2017-11-06T11:57:41.850+0000",
      "uuid" : "efb7e55d-7062-4cf8-ab6a-a97cfdee9ffc",
      "inactive" : false,
      "name" : "Infection Control",
      "reference" : "D",
      "_links" : {
        "self" : {
          "href" : "/48"
        },
        "areaOfConcern" : {
          "href" : "/48"
        },
        "standards" : {
          "href" : "/48/standards"
        },
        "checklists" : {
          "href" : "/48/checklists"
        }
      }
    }, {
      "createdDate" : "2017-11-06T11:57:41.985+0000",
      "lastModifiedDate" : "2017-11-06T11:57:41.985+0000",
      "uuid" : "ee90153b-4bc7-4ae9-b1c0-cdd189d36532",
      "inactive" : false,
      "name" : "Support Services",
      "reference" : "E",
      "_links" : {
        "self" : {
          "href" : "/49"
        },
        "areaOfConcern" : {
          "href" : "/49"
        },
        "standards" : {
          "href" : "/49/standards"
        },
        "checklists" : {
          "href" : "/49/checklists"
        }
      }
    }, {
      "createdDate" : "2017-11-06T11:57:42.078+0000",
      "lastModifiedDate" : "2017-11-06T11:57:42.078+0000",
      "uuid" : "8774d2e5-c86c-4e5a-9774-382d6da8d151",
      "inactive" : false,
      "name" : "Hygiene Promotion",
      "reference" : "F",
      "_links" : {
        "self" : {
          "href" : "/50"
        },
        "areaOfConcern" : {
          "href" : "/50"
        },
        "standards" : {
          "href" : "/50/standards"
        },
        "checklists" : {
          "href" : "/50/checklists"
        }
      }
    }, {
      "createdDate" : "2017-12-02T07:12:32.022+0000",
      "lastModifiedDate" : "2017-12-02T07:12:32.022+0000",
      "uuid" : "f72c8b24-1fb4-41d1-996b-d2b321ab3e06",
      "inactive" : false,
      "name" : "Service Provision",
      "reference" : "A",
      "_links" : {
        "self" : {
          "href" : "/51"
        },
        "areaOfConcern" : {
          "href" : "/51"
        },
        "standards" : {
          "href" : "/51/standards"
        },
        "checklists" : {
          "href" : "/51/checklists"
        }
      }
    }, {
      "createdDate" : "2017-12-02T07:12:32.084+0000",
      "lastModifiedDate" : "2017-12-02T07:12:32.084+0000",
      "uuid" : "f58a020c-5dad-4d48-b9b3-1faf21e505ce",
      "inactive" : false,
      "name" : "Patient Rights",
      "reference" : "B",
      "_links" : {
        "self" : {
          "href" : "/52"
        },
        "areaOfConcern" : {
          "href" : "/52"
        },
        "standards" : {
          "href" : "/52/standards"
        },
        "checklists" : {
          "href" : "/52/checklists"
        }
      }
    }, {
      "createdDate" : "2017-12-02T07:12:32.160+0000",
      "lastModifiedDate" : "2017-12-02T07:12:32.160+0000",
      "uuid" : "f18ac4f5-212b-4673-b5ba-e90bc7d22be7",
      "inactive" : false,
      "name" : "Inputs",
      "reference" : "C",
      "_links" : {
        "self" : {
          "href" : "/53"
        },
        "areaOfConcern" : {
          "href" : "/53"
        },
        "standards" : {
          "href" : "/53/standards"
        },
        "checklists" : {
          "href" : "/53/checklists"
        }
      }
    }, {
      "createdDate" : "2017-12-02T07:12:32.364+0000",
      "lastModifiedDate" : "2017-12-02T07:12:32.364+0000",
      "uuid" : "d55e6fbc-17d3-45cd-b4a4-c34ce13673e2",
      "inactive" : false,
      "name" : "Support Services",
      "reference" : "D",
      "_links" : {
        "self" : {
          "href" : "/54"
        },
        "areaOfConcern" : {
          "href" : "/54"
        },
        "standards" : {
          "href" : "/54/standards"
        },
        "checklists" : {
          "href" : "/54/checklists"
        }
      }
    }, {
      "createdDate" : "2017-12-02T07:12:32.518+0000",
      "lastModifiedDate" : "2017-12-02T07:12:32.518+0000",
      "uuid" : "1ae8c50c-c840-440d-8916-def6900c54d7",
      "inactive" : false,
      "name" : "Clinical Services",
      "reference" : "E",
      "_links" : {
        "self" : {
          "href" : "/55"
        },
        "areaOfConcern" : {
          "href" : "/55"
        },
        "standards" : {
          "href" : "/55/standards"
        },
        "checklists" : {
          "href" : "/55/checklists"
        }
      }
    }, {
      "createdDate" : "2017-12-02T07:12:32.769+0000",
      "lastModifiedDate" : "2017-12-02T07:12:32.769+0000",
      "uuid" : "ec3ce216-f5ce-4677-99fe-11e2901e7bc5",
      "inactive" : false,
      "name" : "Infection Control",
      "reference" : "F",
      "_links" : {
        "self" : {
          "href" : "/56"
        },
        "areaOfConcern" : {
          "href" : "/56"
        },
        "standards" : {
          "href" : "/56/standards"
        },
        "checklists" : {
          "href" : "/56/checklists"
        }
      }
    }, {
      "createdDate" : "2017-12-02T07:12:32.948+0000",
      "lastModifiedDate" : "2017-12-02T07:12:32.948+0000",
      "uuid" : "451d5939-8eca-45c4-a0cb-eabf241eebec",
      "inactive" : false,
      "name" : "Quality Management",
      "reference" : "G",
      "_links" : {
        "self" : {
          "href" : "/57"
        },
        "areaOfConcern" : {
          "href" : "/57"
        },
        "standards" : {
          "href" : "/57/standards"
        },
        "checklists" : {
          "href" : "/57/checklists"
        }
      }
    }, {
      "createdDate" : "2017-12-02T07:12:33.052+0000",
      "lastModifiedDate" : "2017-12-02T07:12:33.052+0000",
      "uuid" : "bfa3b38a-64c3-42cf-ad22-88d5dff79c06",
      "inactive" : false,
      "name" : "Outcome",
      "reference" : "H",
      "_links" : {
        "self" : {
          "href" : "/58"
        },
        "areaOfConcern" : {
          "href" : "/58"
        },
        "standards" : {
          "href" : "/58/standards"
        },
        "checklists" : {
          "href" : "/58/checklists"
        }
      }
    }, {
      "createdDate" : "2017-12-02T07:12:33.412+0000",
      "lastModifiedDate" : "2017-12-02T07:12:33.412+0000",
      "uuid" : "b54270c8-9a6e-4b65-8bbd-e30aefb79e4e",
      "inactive" : false,
      "name" : "MNH Programme",
      "reference" : "Y",
      "_links" : {
        "self" : {
          "href" : "/61"
        },
        "areaOfConcern" : {
          "href" : "/61"
        },
        "standards" : {
          "href" : "/61/standards"
        },
        "checklists" : {
          "href" : "/61/checklists"
        }
      }
    } ]
  },
  "_links" : {
    "self" : {
      "href" : "1900-01-01T00:00:00.001Z&size=200&page=0"
    }
  },
  "page" : {
    "size" : 200,
    "totalElements" : 59,
    "totalPages" : 1,
    "number" : 0
  }
}